labcsv/__init__.py
labcsv/lab_reader.py
labcsv-1.0.4.dist-info/LICENSE
labcsv-1.0.4.dist-info/METADATA
labcsv-1.0.4.dist-info/WHEEL
labcsv-1.0.4.dist-info/top_level.txt
labcsv-1.0.4.dist-info/RECORD
