Metadata-Version: 2.1
Name: labcsv
Version: 1.0.4
Summary: Get data column by column from the CSV file export by lab.js. Use Pandas.
Home-page: https://github.com/s-n-1-0/labcsv.py
Download-URL: https://github.com/s-n-1-0/labcsv.py
Author: sn-10
License: MIT
Keywords: labjs,lab.js
License-File: LICENSE
Requires-Dist: numpy (>=1.20.3)
Requires-Dist: pandas (>=1.3.4)
